<?xml version="1.0" encoding="UTF-8"?>
<manifest>

  <!-- AOSP -->
  <remote name="aosp"
          fetch="https://android.googlesource.com"
          sync-c="true"
          sync-tags="false"
          review="https://android-review.googlesource.com/"
          revision="refs/tags/android-13.0.0_r13"/>

  <!-- CLO -->
  <remote name="clo_system"
          fetch="https://git.codelinaro.org/clo/la"
          sync-c="true"
          sync-tags="false"
          review="codelinaro.org"/>

  <remote name="clo_vendor"
          fetch="https://git.codelinaro.org/clo/la"
          sync-c="true"
          sync-tags="false"
          review="codelinaro.org"
          revision="refs/tags/LA.UM.9.14.r1-20200-LAHAINA.QSSI13.0"/>

  <default revision="refs/tags/LA.QSSI.13.0.r1-08300-qssi.0"
           remote="clo_system"/>

  <include name="system.xml"/>
  <include name="vendor.xml"/>

  <!-- 404 -->
  <include name="404.xml"/>
  <include name="obsolete.xml"/>

</manifest>
